phyunit/__init__.py
phyunit/compound.py
phyunit/compound.pyi
phyunit/dimension.py
phyunit/dimension.pyi
phyunit/dimensionconst.py
phyunit/exceptions.py
phyunit/multiunit.py
phyunit/quantity.py
phyunit/quantity.pyi
phyunit/singleunit.py
phyunit/SI/__init__.py
phyunit/SI/constants.py
phyunit/SI/conversion.py
phyunit/SI/prefixes.py
phyunit/SI/units.py
phyunit/_data/prefixes.py
phyunit/_data/units.py
phyunit/_data/values.py
phyunit/utils/__init__.py
phyunit/utils/constclass.py
phyunit/utils/iter_tools.py
phyunit/utils/number.py
phyunit/utils/numpy_phony.py
phyunit/utils/numpy_ufunc.py
phyunit/utils/operator.py
phyunit/utils/special_char.py
phyunit/utils/valuetype.py
phyunit-0.2.1.dist-info/licenses/LICENSE
phyunit-0.2.1.dist-info/METADATA
phyunit-0.2.1.dist-info/WHEEL
phyunit-0.2.1.dist-info/top_level.txt
phyunit-0.2.1.dist-info/RECORD
