Metadata-Version: 2.4
Name: phyunit
Version: 0.2.1
Summary: A package for physical units.
Author-email: Dait <daitthu@qq.com>
License-Expression: GPL-3.0-only
Project-URL: Homepage, https://github.com/DaitTHU/phyunit
Project-URL: Issues, https://github.com/DaitTHU/phyunit/issues
Keywords: physics,units,quantities,SI,physical constants
Classifier: Programming Language :: Python :: 3
Classifier: Operating System :: OS Independent
Classifier: Topic :: Scientific/Engineering :: Physics
Classifier: Typing :: Typed
Requires-Python: >=3.10
License-File: LICENSE
Dynamic: license-file
